remediate/__init__.py
remediate/aws.py
remediate/runbook/AWS-CFM-003.py
remediate/runbook/AWS-CLT-002.py
remediate/runbook/AWS-CLT-004.py
remediate/runbook/AWS-CLT-005.py
remediate/runbook/AWS-CLT-006.py
remediate/runbook/AWS-CONFIG-001.py
remediate/runbook/AWS-EC2-001.py
remediate/runbook/AWS-EC2-002.py
remediate/runbook/AWS-EC2-003.py
remediate/runbook/AWS-EC2-004.py
remediate/runbook/AWS-EC2-031.py
remediate/runbook/AWS-EC2-036.py
remediate/runbook/AWS-EC2-038.py
remediate/runbook/AWS-EC2-039.py
remediate/runbook/AWS-EC2-042.py
remediate/runbook/AWS-ELB-009.py
remediate/runbook/AWS-ELB-012.py
remediate/runbook/AWS-ELB-013.py
remediate/runbook/AWS-ELB-015.py
remediate/runbook/AWS-IAM-002.py
remediate/runbook/AWS-IAM-016.py
remediate/runbook/AWS-IAM-018.py
remediate/runbook/AWS-KMS-001.py
remediate/runbook/AWS-KMS-002.py
remediate/runbook/AWS-RDS-005.py
remediate/runbook/AWS-RDS-007.py
remediate/runbook/AWS-RDS-010.py
remediate/runbook/AWS-RDS-011.py
remediate/runbook/AWS-REDSHIFT-001.py
remediate/runbook/AWS-SSS-001.py
remediate/runbook/AWS-SSS-008.py
remediate/runbook/AWS-SSS-009.py
remediate/runbook/AWS-SSS-014.py
remediate/runbook/AWS-TEST-001.py
remediate/runbook/AWS-VPC-013.py
remediate/runbook/AWS-VPC-020.py
remediate/runbook/AWS-VPC-Default.py
remediate/runbook/AWS_IAM_015.py
remediate/runbook/__init__.py
remediate-0.0.16.dist-info/LICENSE
remediate-0.0.16.dist-info/LICENSE.txt
remediate-0.0.16.dist-info/METADATA
remediate-0.0.16.dist-info/WHEEL
remediate-0.0.16.dist-info/top_level.txt
remediate-0.0.16.dist-info/RECORD
