Metadata-Version: 2.1
Name: remediate
Version: 0.0.16
Summary: integrate previously written remediation code into Demisto
Home-page: https://github.com/cloudcraeft/remediate
Author: cloudcraeft
Author-email: cloudcraeft@outloook.com
License: MIT
Platform: UNKNOWN
Requires-Python: ~=3.7
Requires-Dist: boto3
